design/checkpoint_01/harmony_py_mock.py
examples/helper.py
harmony/__init__.py
harmony/auth.py
harmony/client.py
harmony/config.py
harmony/request.py
harmony/util.py
harmony_py-1.3.0.dist-info/licenses/LICENSE
internal/genparams.py
harmony_py-1.3.0.dist-info/METADATA
harmony_py-1.3.0.dist-info/WHEEL
harmony_py-1.3.0.dist-info/top_level.txt
harmony_py-1.3.0.dist-info/RECORD
