Metadata-Version: 2.4
Name: harmony-py
Version: 1.3.0
Summary: Python library for integrating with NASA's Harmony Services.
Author-email: NASA EOSDIS Harmony Team <christopher.d.durbin@nasa.gov>
License: Copyright © 2019-2021 United States Government as represented by the Administrator of the National Aeronautics and Space Administration. All Rights Reserved.
Project-URL: Homepage, https://github.com/nasa/harmony-py
Project-URL: Documentation, https://harmony-py.readthedocs.io/en/main/
Project-URL: Repository, https://github.com/nasa/harmony-py.git
Keywords: nasa,harmony,remote-sensing,science,geoscience
Classifier: Development Status :: 3 - Alpha
Classifier: Intended Audience :: Developers
Classifier: Intended Audience :: Science/Research
Classifier: Programming Language :: Python :: 3
Classifier: Programming Language :: Python :: 3.9
Classifier: Programming Language :: Python :: 3.10
Classifier: Programming Language :: Python :: 3.11
Classifier: Programming Language :: Python :: 3.12
Classifier: Programming Language :: Python :: 3.13
Classifier: Programming Language :: Python :: 3 :: Only
Requires-Python: <4,>=3.9
License-File: LICENSE
Requires-Dist: python-dateutil~=2.9
Requires-Dist: python-dotenv~=0.20.0
Requires-Dist: progressbar2~=4.2.0
Requires-Dist: requests~=2.32.3
Requires-Dist: sphinxcontrib-napoleon~=0.7
Requires-Dist: curlify~=2.2.1
Requires-Dist: shapely~=2.0.4
Provides-Extra: dev
Requires-Dist: coverage~=7.4; extra == "dev"
Requires-Dist: flake8~=7.1.1; extra == "dev"
Requires-Dist: hypothesis~=6.103; extra == "dev"
Requires-Dist: PyYAML~=6.0.1; extra == "dev"
Requires-Dist: pytest~=8.2; extra == "dev"
Requires-Dist: pytest-cov~=5.0; extra == "dev"
Requires-Dist: pytest-mock~=3.14; extra == "dev"
Requires-Dist: pytest-watch~=4.2; extra == "dev"
Requires-Dist: responses~=0.25.6; extra == "dev"
Provides-Extra: docs
Requires-Dist: curlify~=2.2.1; extra == "docs"
Requires-Dist: Jinja2~=3.1.2; extra == "docs"
Requires-Dist: load-dotenv~=0.1.0; extra == "docs"
Requires-Dist: nbconvert~=7.10.0; extra == "docs"
Requires-Dist: progressbar2~=4.2.0; extra == "docs"
Requires-Dist: sphinx~=7.1.2; extra == "docs"
Requires-Dist: sphinx-rtd-theme~=1.3.0; extra == "docs"
Requires-Dist: shapely~=2.0.4; extra == "docs"
Provides-Extra: examples
Requires-Dist: boto3~=1.28; extra == "examples"
Requires-Dist: intake-stac~=0.4.0; extra == "examples"
Requires-Dist: ipyplot~=1.1; extra == "examples"
Requires-Dist: ipywidgets~=8.1; extra == "examples"
Requires-Dist: jupyterlab~=4.0; extra == "examples"
Requires-Dist: matplotlib~=3.8; extra == "examples"
Requires-Dist: netCDF4~=1.6; extra == "examples"
Requires-Dist: numpy~=1.26; extra == "examples"
Requires-Dist: pillow~=10.1; extra == "examples"
Requires-Dist: pystac~=1.9.0; extra == "examples"
Requires-Dist: rasterio~=1.3; extra == "examples"
Dynamic: license-file
